Workbook

Sheet Supuestos
A1: Supuestos — celdas amarillas editables. Todo lo demás se recalcula.
A3: Tipo de cambio de referencia | B3: 1500 | C3: BNA 07-09-2026: 1.480/1.530. No hay TC verificado en resúmenes.
A4: Valor UVA | B4: 2106.13 | C4: BCRA 07-09-2026
A5: Depto A (viven) US$ | B5: 145000 | C5: Dicho por Agustina. 65 m2, Plaza Irlanda.
A6: Depto B (en pago) US$ | B6: 140000 | C6: Dicho por Agustina. Cid Campeador.
A7: Saldo pendiente de B (US$) | B7: 0 | C7: DESCONOCIDO. Pedir a Maxi: cuánto falta, moneda, tasa, plazo.
A8: Depto C objetivo US$ | B8: 140000 | C8: Mismas condiciones que B.
A9: m2 del depto grande | B9: 95 | C9: 3-4 ambientes
A10: US$/m2 Caballito | B10: 2500 | C10: Abr-2026: 1.800 sur a 2.800 Primera Junta
A11: Costos de compra (% del precio) | B11: 0.08 | C11: Sellos 1,75% + escribano ~2% + comisión 4%+IVA
A12: Costos de venta (% del precio) | B12: 0.051 | C12: Comisión 3%+IVA + ITI 1,5%
A13: Alquiler 2 amb 65 m2 ($/mes) | B13: 900000 | C13: Zonaprop abr-2026: 2 amb CABA $834k; Caballito 600-800k para 35-45 m2. Verificar con relevamiento.
A14: Vacancia (fracción del año) | B14: 0.083333333 | C14: 1 mes por año
... A17: TNA hipotecario 2da vivienda / inversión (+UVA) | B17: 0.15 | C17: Provincia sin cuenta sueldo / 2da vivienda
A18: Plazo (meses) | B18: 360
A19: Financiación máxima (LTV) | B19: 0.75 | C19: 75-80% según banco
A20: Cuota / ingreso neto máximo | B20: 0.25 | C20: Bancos: 20-30%
A21: ORT neto ($/mes, demostrable) | B21: 426000 | C21: Recibo de sueldo
A22: Roxom (USDT/mes) | B22: 1600 | C22: NO demostrable hasta facturar por monotributo
A23: Roxom si sale la review (USDT/mes) | B23: 2400
A24: CFTEA préstamo personal | B24: 0.9 | C24: Sep-2026: 58,9% premium a 320%

Sheet Escenarios
A1: Escenarios comparados | D1: Cómo se calcula
A3: Alquiler 2 amb
A4: Alquiler bruto US$/mes | B4: =Supuestos!$B$13/Supuestos!$B$3 | D4: alquiler / TC
A5: Alquiler neto US$/mes | B5: =Supuestos!$B$13*(1-Supuestos!$B$14)*(1-Supuestos!$B$15)/Supuestos!$B$3 | D5: neto de vacancia y gastos
A6: Yield bruto anual | B6: =B4*12/Supuestos!$B$6 | D6: sobre el valor del depto
A7: Yield neto anual | B7: =B5*12/Supuestos!$B$6
A9: E1 — Comprar C con hipoteca (viven en A, alquilan B y C)
A10: Costo total de C con gastos US$ | B10: =Supuestos!$B$8*(1+Supuestos!$B$11)
A11: Préstamo (LTV) US$ | B11: =Supuestos!$B$8*Supuestos!$B$19
A12: Efectivo necesario US$ | B12: =B10-B11 | D12: precio + gastos − préstamo. ¿De dónde sale?
A13: Cuota inicial UVA+1ra $ | B13: =-PMT(Supuestos!$B$16/12,Supuestos!$B$18,B11*Supuestos!$B$3) | D13: sube con UVA cada mes
A14: Cuota inicial UVA+1ra US$ | B14: =B13/Supuestos!$B$3
A15: Alquiler neto cubre la cuota (1ra) | B15: =B5*Supuestos!$B$3/B13
A16: Flujo mensual con C alquilado (1ra) US$ | B16: =B5-B13/Supuestos!$B$3 | D16: negativo = hay que poner plata todos los meses
A17: Ingreso neto demostrable mínimo del tomador (1ra) $ | B17: =B13/Supuestos!$B$20 | D17: cuota / 25%
A18: Cuota inicial UVA+2da $ | B18: =-PMT(Supuestos!$B$17/12,Supuestos!$B$18,B11*Supuestos!$B$3) | D18: sube con UVA cada mes
A19: Cuota inicial UVA+2da US$ | B19: =B18/Supuestos!$B$3
A20: Alquiler neto cubre la cuota (2da) | B20: =B5*Supuestos!$B$3/B18
A21: Flujo mensual con C alquilado (2da) US$ | B21: =B5-B18/Supuestos!$B$3 | D21: negativo = hay que poner plata todos los meses
A22: Ingreso neto demostrable mínimo del tomador (2da) $ | B22: =B18/Supuestos!$B$20 | D22: cuota / 25%
A23: Flujo total E1: renta B + renta C − cuota C (2da vivienda) US$ | B23: =B5*2-B18/Supuestos!$B$3 | D23: lo que queda para la pareja cada mes
A25: E2 — Vender A y B, comprar uno grande
A26: Precio depto grande US$ | B26: =Supuestos!$B$9*Supuestos!$B$10
A27: Costo con gastos de compra US$ | B27: =B26*(1+Supuestos!$B$11)
A28: Neto de vender A y B US$ | B28: =(Supuestos!$B$5+Supuestos!$B$6)*(1-Supuestos!$B$12)-Supuestos!$B$7
A29: Fricción total (se pierde) US$ | B29: =(Supuestos!$B$5+Supuestos!$B$6)*Supuestos!$B$12+B26*Supuestos!$B$11 | D29: comisiones, sellos, ITI, escribano
A30: Sobra (+) / falta (−) US$ | B30: =B28-B27
A31: Renta que se pierde al vender B US$/mes | B31: =B5
A33: E3 — Quedarse con A y B, alquilar B, no comprar
A34: Flujo mensual US$ | B34: =B5
A35: Ahorro mensual adicional de la pareja US$ (editar) | B35: 500
A36: Efectivo necesario para C (75% LTV) US$ | B36: =B10-B11 | D36: efectivo necesario
A37: Meses para juntarlo con renta B + ahorro | B37: =B36/(B5+B35)

Sheet Capacidad Agustina
A1: Capacidad hipotecaria de Agustina — cuota ≤ ratio × ingreso neto demostrable
A2: Escenario de ingreso | B2: Ingreso neto demostrable $ | C2: Cuota máx $ | D2: Préstamo US$ (1ra) | E2: Préstamo US$ (2da) | F2: Condición
A3: Hoy: sólo ORT | B3: =Supuestos!$B$21 | C3: =B3*Supuestos!$B$20 | D3: =PV(Supuestos!$B$16/12,Supuestos!$B$18,-C3)/Supuestos!$B$3 | E3: =PV(Supuestos!$B$17/12,Supuestos!$B$18,-C3)/Supuestos!$B$3 | F3: En mora en Galicia Mastercard: ningún banco precalifica hasta salir y que BCRA lo refleje.
A4: ORT + Roxom 1.600 facturado | B4: =Supuestos!$B$21+Supuestos!$B$22*Supuestos!$B$3 | C4: =B4*Supuestos!$B$20 | D4: =PV(Supuestos!$B$16/12,Supuestos!$B$18,-C4)/Supuestos!$B$3 | E4: =PV(Supuestos!$B$17/12,Supuestos!$B$18,-C4)/Supuestos!$B$3 | F4: Requiere 6-12 meses de facturas de monotributo. Cada banco aplica su descuento.
A5: ORT + Roxom 2.400 facturado | B5: =Supuestos!$B$21+Supuestos!$B$23*Supuestos!$B$3 | C5: =B5*Supuestos!$B$20 | D5: =PV(Supuestos!$B$16/12,Supuestos!$B$18,-C5)/Supuestos!$B$3 | E5: =PV(Supuestos!$B$17/12,Supuestos!$B$18,-C5)/Supuestos!$B$3 | F5: Si sale la review y se factura.
A7: Préstamo personal en vez de hipoteca
A8: Costo mensual del préstamo (TEM desde CFTEA) | B8: =(1+Supuestos!$B$24)^(1/12)-1
A9: Renta neta mensual del depto | B9: =Escenarios!B7/12
A10: Carry mensual (renta − costo) | B10: =B9-B8
